nacl_middleware/__init__.py
nacl_middleware/nacl_middleware.py
nacl_middleware/nacl_utils.py
nacl_middleware/utils.py
nacl_middleware-0.0.9.dist-info/METADATA
nacl_middleware-0.0.9.dist-info/WHEEL
nacl_middleware-0.0.9.dist-info/top_level.txt
nacl_middleware-0.0.9.dist-info/RECORD
